[{"caption": "the picture has a black window", "predicate": "has", "target": {"coordinates": [203.2366027832, 97.091674804688, 219.51336669922, 644.93524169922]}, "name": 3249, "source": {"coordinates": [904.11578369141, 148.03507995605, 186.52703857422, 507.61950683594]}, "seconds": 135.375, "object": "a black window", "type": "relation", "subject": "the picture"}, {"caption": "the woman wearing blue shirt", "predicate": "wearing", "target": {"coordinates": [636.12890625, 106.10354614258, 183.32446289062, 343.80798339844]}, "name": 3249, "source": {"coordinates": [904.11578369141, 148.03507995605, 186.52703857422, 507.61950683594]}, "seconds": 135.375, "object": "blue shirt", "type": "relation", "subject": "the woman"}, {"caption": "the building in background", "predicate": "in", "target": {"coordinates": [380.93823242188, 59.199829101562, 157.65313720703, 655.81927490234]}, "name": 3249, "source": {"coordinates": [904.11578369141, 148.03507995605, 186.52703857422, 507.61950683594]}, "seconds": 135.375, "object": "background", "type": "relation", "subject": "the building"}, {"caption": "the woman in front of white", "predicate": "in", "target": {"coordinates": [847.54547119141, 153.67877197266, 136.99731445312, 456.45629882812]}, "name": 3249, "source": {"coordinates": [904.11578369141, 148.03507995605, 186.52703857422, 507.61950683594]}, "seconds": 135.375, "object": "front of white", "type": "relation", "subject": "the woman"}, {"caption": "the woman in front of white", "predicate": "in", "target": {"coordinates": [904.11578369141, 148.03507995605, 186.52703857422, 507.61950683594]}, "name": 3249, "source": {"coordinates": [203.2366027832, 97.091674804688, 219.51336669922, 644.93524169922]}, "seconds": 135.375, "object": "front of white", "type": "relation", "subject": "the woman"}, {"caption": "the woman wearing black shirt", "predicate": "wearing", "target": {"coordinates": [636.12890625, 106.10354614258, 183.32446289062, 343.80798339844]}, "name": 3249, "source": {"coordinates": [203.2366027832, 97.091674804688, 219.51336669922, 644.93524169922]}, "seconds": 135.375, "object": "black shirt", "type": "relation", "subject": "the woman"}, {"caption": "the woman in front of white", "predicate": "in", "target": {"coordinates": [380.93823242188, 59.199829101562, 157.65313720703, 655.81927490234]}, "name": 3249, "source": {"coordinates": [203.2366027832, 97.091674804688, 219.51336669922, 644.93524169922]}, "seconds": 135.375, "object": "front of white", "type": "relation", "subject": "the woman"}, {"caption": "the window on top of the wall", "predicate": "on", "target": {"coordinates": [847.54547119141, 153.67877197266, 136.99731445312, 456.45629882812]}, "name": 3249, "source": {"coordinates": [203.2366027832, 97.091674804688, 219.51336669922, 644.93524169922]}, "seconds": 135.375, "object": "top of the wall", "type": "relation", "subject": "the window"}, {"caption": "the window on top of the wall", "predicate": "on", "target": {"coordinates": [904.11578369141, 148.03507995605, 186.52703857422, 507.61950683594]}, "name": 3249, "source": {"coordinates": [636.12890625, 106.10354614258, 183.32446289062, 343.80798339844]}, "seconds": 135.375, "object": "top of the wall", "type": "relation", "subject": "the window"}, {"caption": "the cat on top of man", "predicate": "on", "target": {"coordinates": [203.2366027832, 97.091674804688, 219.51336669922, 644.93524169922]}, "name": 3249, "source": {"coordinates": [636.12890625, 106.10354614258, 183.32446289062, 343.80798339844]}, "seconds": 135.375, "object": "top of man", "type": "relation", "subject": "the cat"}, {"caption": "the window on top of the wall", "predicate": "on", "target": {"coordinates": [380.93823242188, 59.199829101562, 157.65313720703, 655.81927490234]}, "name": 3249, "source": {"coordinates": [636.12890625, 106.10354614258, 183.32446289062, 343.80798339844]}, "seconds": 135.375, "object": "top of the wall", "type": "relation", "subject": "the window"}, {"caption": "the woman in front of white", "predicate": "in", "target": {"coordinates": [847.54547119141, 153.67877197266, 136.99731445312, 456.45629882812]}, "name": 3249, "source": {"coordinates": [636.12890625, 106.10354614258, 183.32446289062, 343.80798339844]}, "seconds": 135.375, "object": "front of white", "type": "relation", "subject": "the woman"}, {"caption": "the woman in front of white", "predicate": "in", "target": {"coordinates": [904.11578369141, 148.03507995605, 186.52703857422, 507.61950683594]}, "name": 3249, "source": {"coordinates": [380.93823242188, 59.199829101562, 157.65313720703, 655.81927490234]}, "seconds": 135.375, "object": "front of white", "type": "relation", "subject": "the woman"}, {"caption": "the woman wearing black shirt", "predicate": "wearing", "target": {"coordinates": [203.2366027832, 97.091674804688, 219.51336669922, 644.93524169922]}, "name": 3249, "source": {"coordinates": [380.93823242188, 59.199829101562, 157.65313720703, 655.81927490234]}, "seconds": 135.375, "object": "black shirt", "type": "relation", "subject": "the woman"}, {"caption": "the woman wearing black shirt", "predicate": "wearing", "target": {"coordinates": [636.12890625, 106.10354614258, 183.32446289062, 343.80798339844]}, "name": 3249, "source": {"coordinates": [380.93823242188, 59.199829101562, 157.65313720703, 655.81927490234]}, "seconds": 135.375, "object": "black shirt", "type": "relation", "subject": "the woman"}, {"caption": "the building in background", "predicate": "in", "target": {"coordinates": [847.54547119141, 153.67877197266, 136.99731445312, 456.45629882812]}, "name": 3249, "source": {"coordinates": [380.93823242188, 59.199829101562, 157.65313720703, 655.81927490234]}, "seconds": 135.375, "object": "background", "type": "relation", "subject": "the building"}, {"caption": "the building in background", "predicate": "in", "target": {"coordinates": [904.11578369141, 148.03507995605, 186.52703857422, 507.61950683594]}, "name": 3249, "source": {"coordinates": [847.54547119141, 153.67877197266, 136.99731445312, 456.45629882812]}, "seconds": 135.375, "object": "background", "type": "relation", "subject": "the building"}, {"caption": "the people in front of a woman", "predicate": "in", "target": {"coordinates": [203.2366027832, 97.091674804688, 219.51336669922, 644.93524169922]}, "name": 3249, "source": {"coordinates": [847.54547119141, 153.67877197266, 136.99731445312, 456.45629882812]}, "seconds": 135.375, "object": "front of a woman", "type": "relation", "subject": "the people"}, {"caption": "the picture has a black window", "predicate": "has", "target": {"coordinates": [636.12890625, 106.10354614258, 183.32446289062, 343.80798339844]}, "name": 3249, "source": {"coordinates": [847.54547119141, 153.67877197266, 136.99731445312, 456.45629882812]}, "seconds": 135.375, "object": "a black window", "type": "relation", "subject": "the picture"}, {"caption": "the woman wearing blue shirt", "predicate": "wearing", "target": {"coordinates": [380.93823242188, 59.199829101562, 157.65313720703, 655.81927490234]}, "name": 3249, "source": {"coordinates": [847.54547119141, 153.67877197266, 136.99731445312, 456.45629882812]}, "seconds": 135.375, "object": "blue shirt", "type": "relation", "subject": "the woman"}]