[{"caption": "the people in background", "predicate": "in", "target": {"coordinates": [729.69561767578, 23.383972167969, 557.09271240234, 690.38598632812]}, "name": 1938, "source": {"coordinates": [37.7646484375, 69.203063964844, 748.65319824219, 648.49078369141]}, "seconds": 80.75, "object": "background", "type": "relation", "subject": "the people"}, {"caption": "the people in background", "predicate": "in", "target": {"coordinates": [37.7646484375, 69.203063964844, 748.65319824219, 648.49078369141]}, "name": 1938, "source": {"coordinates": [729.69561767578, 23.383972167969, 557.09271240234, 690.38598632812]}, "seconds": 80.75, "object": "background", "type": "relation", "subject": "the people"}]