[{"caption": "the people on top of brown table", "predicate": "on", "target": {"coordinates": [748.66357421875, 30.095581054688, 554.27319335938, 702.09002685547]}, "name": 1941, "source": {"coordinates": [-6.0543212890625, 70.738952636719, 854.10516357422, 654.60632324219]}, "seconds": 80.875, "object": "top of brown table", "type": "relation", "subject": "the people"}, {"caption": "the people on top of brown table", "predicate": "on", "target": {"coordinates": [-6.0543212890625, 70.738952636719, 854.10516357422, 654.60632324219]}, "name": 1941, "source": {"coordinates": [748.66357421875, 30.095581054688, 554.27319335938, 702.09002685547]}, "seconds": 80.875, "object": "top of brown table", "type": "relation", "subject": "the people"}]