[{"caption": "the woman in room", "predicate": "in", "target": {"coordinates": [579.64978027344, 91.729248046875, 457.13439941406, 617.60498046875]}, "name": 1020, "source": {"coordinates": [50.387176513672, -0.85501098632812, 591.4658203125, 750.62414550781]}, "seconds": 42.5, "object": "room", "type": "relation", "subject": "the woman"}, {"caption": "the woman in room", "predicate": "in", "target": {"coordinates": [50.387176513672, -0.85501098632812, 591.4658203125, 750.62414550781]}, "name": 1020, "source": {"coordinates": [579.64978027344, 91.729248046875, 457.13439941406, 617.60498046875]}, "seconds": 42.5, "object": "room", "type": "relation", "subject": "the woman"}]