[{"caption": "the people on top of brown table", "predicate": "on", "target": {"coordinates": [921.83471679688, 43.744812011719, 364.36865234375, 667.15069580078]}, "name": 3518, "source": {"coordinates": [235.14068603516, 75.134002685547, 579.50854492188, 622.73583984375]}, "seconds": 146.58333333333334, "object": "top of brown table", "type": "relation", "subject": "the people"}, {"caption": "the people on top of brown table", "predicate": "on", "target": {"coordinates": [235.14068603516, 75.134002685547, 579.50854492188, 622.73583984375]}, "name": 3518, "source": {"coordinates": [921.83471679688, 43.744812011719, 364.36865234375, 667.15069580078]}, "seconds": 146.58333333333334, "object": "top of brown table", "type": "relation", "subject": "the people"}]