[{"caption": "the man wearing blue shirt", "predicate": "wearing", "target": {"coordinates": [848.95855712891, 111.31567382812, 202.19195556641, 328.38647460938]}, "name": 5868, "source": {"coordinates": [178.48187255859, 275.06066894531, 350.96759033203, 343.92791748047]}, "seconds": 244.5, "object": "blue shirt", "type": "relation", "subject": "the man"}, {"caption": "the man in room", "predicate": "in", "target": {"coordinates": [615.3505859375, 232.14189147949, 128.36047363281, 182.35810852051]}, "name": 5868, "source": {"coordinates": [178.48187255859, 275.06066894531, 350.96759033203, 343.92791748047]}, "seconds": 244.5, "object": "room", "type": "relation", "subject": "the man"}, {"caption": "the man wearing black shirt", "predicate": "wearing", "target": {"coordinates": [721.62689208984, 223.74020385742, 168.00390625, 190.33953857422]}, "name": 5868, "source": {"coordinates": [178.48187255859, 275.06066894531, 350.96759033203, 343.92791748047]}, "seconds": 244.5, "object": "black shirt", "type": "relation", "subject": "the man"}, {"caption": "the woman wearing white shirt", "predicate": "wearing", "target": {"coordinates": [388.57125854492, 222.52941894531, 177.89212036133, 191.38659667969]}, "name": 5868, "source": {"coordinates": [178.48187255859, 275.06066894531, 350.96759033203, 343.92791748047]}, "seconds": 244.5, "object": "white shirt", "type": "relation", "subject": "the woman"}, {"caption": "the woman wearing white shirt", "predicate": "wearing", "target": {"coordinates": [178.48187255859, 275.06066894531, 350.96759033203, 343.92791748047]}, "name": 5868, "source": {"coordinates": [848.95855712891, 111.31567382812, 202.19195556641, 328.38647460938]}, "seconds": 244.5, "object": "white shirt", "type": "relation", "subject": "the woman"}, {"caption": "the people in background", "predicate": "in", "target": {"coordinates": [615.3505859375, 232.14189147949, 128.36047363281, 182.35810852051]}, "name": 5868, "source": {"coordinates": [848.95855712891, 111.31567382812, 202.19195556641, 328.38647460938]}, "seconds": 244.5, "object": "background", "type": "relation", "subject": "the people"}, {"caption": "the woman wearing white shirt", "predicate": "wearing", "target": {"coordinates": [721.62689208984, 223.74020385742, 168.00390625, 190.33953857422]}, "name": 5868, "source": {"coordinates": [848.95855712891, 111.31567382812, 202.19195556641, 328.38647460938]}, "seconds": 244.5, "object": "white shirt", "type": "relation", "subject": "the woman"}, {"caption": "the shirt on man", "predicate": "on", "target": {"coordinates": [388.57125854492, 222.52941894531, 177.89212036133, 191.38659667969]}, "name": 5868, "source": {"coordinates": [848.95855712891, 111.31567382812, 202.19195556641, 328.38647460938]}, "seconds": 244.5, "object": "man", "type": "relation", "subject": "the shirt"}, {"caption": "the shirt on man", "predicate": "on", "target": {"coordinates": [178.48187255859, 275.06066894531, 350.96759033203, 343.92791748047]}, "name": 5868, "source": {"coordinates": [615.3505859375, 232.14189147949, 128.36047363281, 182.35810852051]}, "seconds": 244.5, "object": "man", "type": "relation", "subject": "the shirt"}, {"caption": "the white shirt on the people", "predicate": "on", "target": {"coordinates": [848.95855712891, 111.31567382812, 202.19195556641, 328.38647460938]}, "name": 5868, "source": {"coordinates": [615.3505859375, 232.14189147949, 128.36047363281, 182.35810852051]}, "seconds": 244.5, "object": "the people", "type": "relation", "subject": "the white shirt"}, {"caption": "the shirt on man", "predicate": "on", "target": {"coordinates": [721.62689208984, 223.74020385742, 168.00390625, 190.33953857422]}, "name": 5868, "source": {"coordinates": [615.3505859375, 232.14189147949, 128.36047363281, 182.35810852051]}, "seconds": 244.5, "object": "man", "type": "relation", "subject": "the shirt"}, {"caption": "the woman wearing white shirt", "predicate": "wearing", "target": {"coordinates": [388.57125854492, 222.52941894531, 177.89212036133, 191.38659667969]}, "name": 5868, "source": {"coordinates": [615.3505859375, 232.14189147949, 128.36047363281, 182.35810852051]}, "seconds": 244.5, "object": "white shirt", "type": "relation", "subject": "the woman"}, {"caption": "the woman wearing white shirt", "predicate": "wearing", "target": {"coordinates": [178.48187255859, 275.06066894531, 350.96759033203, 343.92791748047]}, "name": 5868, "source": {"coordinates": [721.62689208984, 223.74020385742, 168.00390625, 190.33953857422]}, "seconds": 244.5, "object": "white shirt", "type": "relation", "subject": "the woman"}, {"caption": "the people in background", "predicate": "in", "target": {"coordinates": [848.95855712891, 111.31567382812, 202.19195556641, 328.38647460938]}, "name": 5868, "source": {"coordinates": [721.62689208984, 223.74020385742, 168.00390625, 190.33953857422]}, "seconds": 244.5, "object": "background", "type": "relation", "subject": "the people"}, {"caption": "the man wearing white shirt", "predicate": "wearing", "target": {"coordinates": [615.3505859375, 232.14189147949, 128.36047363281, 182.35810852051]}, "name": 5868, "source": {"coordinates": [721.62689208984, 223.74020385742, 168.00390625, 190.33953857422]}, "seconds": 244.5, "object": "white shirt", "type": "relation", "subject": "the man"}, {"caption": "the man wearing black shirt", "predicate": "wearing", "target": {"coordinates": [388.57125854492, 222.52941894531, 177.89212036133, 191.38659667969]}, "name": 5868, "source": {"coordinates": [721.62689208984, 223.74020385742, 168.00390625, 190.33953857422]}, "seconds": 244.5, "object": "black shirt", "type": "relation", "subject": "the man"}, {"caption": "the man wearing black shirt", "predicate": "wearing", "target": {"coordinates": [178.48187255859, 275.06066894531, 350.96759033203, 343.92791748047]}, "name": 5868, "source": {"coordinates": [388.57125854492, 222.52941894531, 177.89212036133, 191.38659667969]}, "seconds": 244.5, "object": "black shirt", "type": "relation", "subject": "the man"}, {"caption": "the man in the room", "predicate": "in", "target": {"coordinates": [848.95855712891, 111.31567382812, 202.19195556641, 328.38647460938]}, "name": 5868, "source": {"coordinates": [388.57125854492, 222.52941894531, 177.89212036133, 191.38659667969]}, "seconds": 244.5, "object": "the room", "type": "relation", "subject": "the man"}, {"caption": "the man wearing white shirt", "predicate": "wearing", "target": {"coordinates": [615.3505859375, 232.14189147949, 128.36047363281, 182.35810852051]}, "name": 5868, "source": {"coordinates": [388.57125854492, 222.52941894531, 177.89212036133, 191.38659667969]}, "seconds": 244.5, "object": "white shirt", "type": "relation", "subject": "the man"}, {"caption": "the man in room", "predicate": "in", "target": {"coordinates": [721.62689208984, 223.74020385742, 168.00390625, 190.33953857422]}, "name": 5868, "source": {"coordinates": [388.57125854492, 222.52941894531, 177.89212036133, 191.38659667969]}, "seconds": 244.5, "object": "room", "type": "relation", "subject": "the man"}]