[{"caption": "the woman in front of white", "predicate": "in", "target": {"coordinates": [299.626953125, 118.4914855957, 699.00744628906, 609.44030761719]}, "name": 2050, "source": {"coordinates": [938.71826171875, 428.57122802734, 339.94970703125, 289.03979492188]}, "seconds": 85.41666666666667, "object": "front of white", "type": "relation", "subject": "the woman"}, {"caption": "the woman in front of white", "predicate": "in", "target": {"coordinates": [938.71826171875, 428.57122802734, 339.94970703125, 289.03979492188]}, "name": 2050, "source": {"coordinates": [299.626953125, 118.4914855957, 699.00744628906, 609.44030761719]}, "seconds": 85.41666666666667, "object": "front of white", "type": "relation", "subject": "the woman"}]