[{"caption": "the people in background", "predicate": "in", "target": {"coordinates": [917, 331, 353, 390]}, "name": 329, "source": {"coordinates": [406, 74, 407, 650]}, "seconds": 13.708333333333334, "object": "background", "type": "relation", "subject": "the people"}, {"caption": "the people in background", "predicate": "in", "target": {"coordinates": [406, 74, 407, 650]}, "name": 329, "source": {"coordinates": [917, 331, 353, 390]}, "seconds": 13.708333333333334, "object": "background", "type": "relation", "subject": "the people"}]