[{"caption": "the woman has head", "predicate": "has", "target": {"coordinates": [437.5, 113.5, 152, 171]}, "name": 1352, "source": {"coordinates": [826.5, 211.5, 358, 307]}, "seconds": 56.333333333333336, "object": "head", "type": "relation", "subject": "the woman"}, {"caption": "the building in background", "predicate": "in", "target": {"coordinates": [683.5, 59.5, 87, 182]}, "name": 1352, "source": {"coordinates": [826.5, 211.5, 358, 307]}, "seconds": 56.333333333333336, "object": "background", "type": "relation", "subject": "the building"}, {"caption": "the building in background", "predicate": "in", "target": {"coordinates": [1127.5, 138.5, 146, 266]}, "name": 1352, "source": {"coordinates": [826.5, 211.5, 358, 307]}, "seconds": 56.333333333333336, "object": "background", "type": "relation", "subject": "the building"}, {"caption": "the people in front of white shirt", "predicate": "in", "target": {"coordinates": [821.5, 65.5, 109, 170]}, "name": 1352, "source": {"coordinates": [826.5, 211.5, 358, 307]}, "seconds": 56.333333333333336, "object": "front of white shirt", "type": "relation", "subject": "the people"}, {"caption": "the man wearing blue shirt", "predicate": "wearing", "target": {"coordinates": [587.5, 242.5, 308, 280]}, "name": 1352, "source": {"coordinates": [826.5, 211.5, 358, 307]}, "seconds": 56.333333333333336, "object": "blue shirt", "type": "relation", "subject": "the man"}, {"caption": "the light on the wall", "predicate": "on", "target": {"coordinates": [159.5, 159.5, 252, 331]}, "name": 1352, "source": {"coordinates": [826.5, 211.5, 358, 307]}, "seconds": 56.333333333333336, "object": "the wall", "type": "relation", "subject": "the light"}, {"caption": "the light on the wall", "predicate": "on", "target": {"coordinates": [826.5, 211.5, 358, 307]}, "name": 1352, "source": {"coordinates": [437.5, 113.5, 152, 171]}, "seconds": 56.333333333333336, "object": "the wall", "type": "relation", "subject": "the light"}, {"caption": "the light on the wall", "predicate": "on", "target": {"coordinates": [683.5, 59.5, 87, 182]}, "name": 1352, "source": {"coordinates": [437.5, 113.5, 152, 171]}, "seconds": 56.333333333333336, "object": "the wall", "type": "relation", "subject": "the light"}, {"caption": "the light on wall", "predicate": "on", "target": {"coordinates": [1127.5, 138.5, 146, 266]}, "name": 1352, "source": {"coordinates": [437.5, 113.5, 152, 171]}, "seconds": 56.333333333333336, "object": "wall", "type": "relation", "subject": "the light"}, {"caption": "the shadow on white shirt", "predicate": "on", "target": {"coordinates": [821.5, 65.5, 109, 170]}, "name": 1352, "source": {"coordinates": [437.5, 113.5, 152, 171]}, "seconds": 56.333333333333336, "object": "white shirt", "type": "relation", "subject": "the shadow"}, {"caption": "the light on white shirt", "predicate": "on", "target": {"coordinates": [587.5, 242.5, 308, 280]}, "name": 1352, "source": {"coordinates": [437.5, 113.5, 152, 171]}, "seconds": 56.333333333333336, "object": "white shirt", "type": "relation", "subject": "the light"}, {"caption": "the woman in front of white", "predicate": "in", "target": {"coordinates": [159.5, 159.5, 252, 331]}, "name": 1352, "source": {"coordinates": [437.5, 113.5, 152, 171]}, "seconds": 56.333333333333336, "object": "front of white", "type": "relation", "subject": "the woman"}, {"caption": "the woman in front of white", "predicate": "in", "target": {"coordinates": [826.5, 211.5, 358, 307]}, "name": 1352, "source": {"coordinates": [683.5, 59.5, 87, 182]}, "seconds": 56.333333333333336, "object": "front of white", "type": "relation", "subject": "the woman"}, {"caption": "the woman wearing black shirt", "predicate": "wearing", "target": {"coordinates": [437.5, 113.5, 152, 171]}, "name": 1352, "source": {"coordinates": [683.5, 59.5, 87, 182]}, "seconds": 56.333333333333336, "object": "black shirt", "type": "relation", "subject": "the woman"}, {"caption": "the woman in front of white", "predicate": "in", "target": {"coordinates": [1127.5, 138.5, 146, 266]}, "name": 1352, "source": {"coordinates": [683.5, 59.5, 87, 182]}, "seconds": 56.333333333333336, "object": "front of white", "type": "relation", "subject": "the woman"}, {"caption": "the woman wearing black shirt", "predicate": "wearing", "target": {"coordinates": [821.5, 65.5, 109, 170]}, "name": 1352, "source": {"coordinates": [683.5, 59.5, 87, 182]}, "seconds": 56.333333333333336, "object": "black shirt", "type": "relation", "subject": "the woman"}, {"caption": "the woman wearing blue shirt", "predicate": "wearing", "target": {"coordinates": [587.5, 242.5, 308, 280]}, "name": 1352, "source": {"coordinates": [683.5, 59.5, 87, 182]}, "seconds": 56.333333333333336, "object": "blue shirt", "type": "relation", "subject": "the woman"}, {"caption": "the people in background", "predicate": "in", "target": {"coordinates": [159.5, 159.5, 252, 331]}, "name": 1352, "source": {"coordinates": [683.5, 59.5, 87, 182]}, "seconds": 56.333333333333336, "object": "background", "type": "relation", "subject": "the people"}, {"caption": "the people in background", "predicate": "in", "target": {"coordinates": [826.5, 211.5, 358, 307]}, "name": 1352, "source": {"coordinates": [1127.5, 138.5, 146, 266]}, "seconds": 56.333333333333336, "object": "background", "type": "relation", "subject": "the people"}, {"caption": "the wall has a black", "predicate": "has", "target": {"coordinates": [437.5, 113.5, 152, 171]}, "name": 1352, "source": {"coordinates": [1127.5, 138.5, 146, 266]}, "seconds": 56.333333333333336, "object": "a black", "type": "relation", "subject": "the wall"}, {"caption": "the woman has head", "predicate": "has", "target": {"coordinates": [683.5, 59.5, 87, 182]}, "name": 1352, "source": {"coordinates": [1127.5, 138.5, 146, 266]}, "seconds": 56.333333333333336, "object": "head", "type": "relation", "subject": "the woman"}, {"caption": "the people in front of white shirt", "predicate": "in", "target": {"coordinates": [821.5, 65.5, 109, 170]}, "name": 1352, "source": {"coordinates": [1127.5, 138.5, 146, 266]}, "seconds": 56.333333333333336, "object": "front of white shirt", "type": "relation", "subject": "the people"}, {"caption": "the man wearing blue shirt", "predicate": "wearing", "target": {"coordinates": [587.5, 242.5, 308, 280]}, "name": 1352, "source": {"coordinates": [1127.5, 138.5, 146, 266]}, "seconds": 56.333333333333336, "object": "blue shirt", "type": "relation", "subject": "the man"}, {"caption": "the people in background", "predicate": "in", "target": {"coordinates": [159.5, 159.5, 252, 331]}, "name": 1352, "source": {"coordinates": [1127.5, 138.5, 146, 266]}, "seconds": 56.333333333333336, "object": "background", "type": "relation", "subject": "the people"}, {"caption": "the people in background", "predicate": "in", "target": {"coordinates": [826.5, 211.5, 358, 307]}, "name": 1352, "source": {"coordinates": [821.5, 65.5, 109, 170]}, "seconds": 56.333333333333336, "object": "background", "type": "relation", "subject": "the people"}, {"caption": "the wall has a black", "predicate": "has", "target": {"coordinates": [437.5, 113.5, 152, 171]}, "name": 1352, "source": {"coordinates": [821.5, 65.5, 109, 170]}, "seconds": 56.333333333333336, "object": "a black", "type": "relation", "subject": "the wall"}, {"caption": "the woman has head", "predicate": "has", "target": {"coordinates": [683.5, 59.5, 87, 182]}, "name": 1352, "source": {"coordinates": [821.5, 65.5, 109, 170]}, "seconds": 56.333333333333336, "object": "head", "type": "relation", "subject": "the woman"}, {"caption": "the people in background", "predicate": "in", "target": {"coordinates": [1127.5, 138.5, 146, 266]}, "name": 1352, "source": {"coordinates": [821.5, 65.5, 109, 170]}, "seconds": 56.333333333333336, "object": "background", "type": "relation", "subject": "the people"}, {"caption": "the man wearing blue shirt", "predicate": "wearing", "target": {"coordinates": [587.5, 242.5, 308, 280]}, "name": 1352, "source": {"coordinates": [821.5, 65.5, 109, 170]}, "seconds": 56.333333333333336, "object": "blue shirt", "type": "relation", "subject": "the man"}, {"caption": "the man in the room", "predicate": "in", "target": {"coordinates": [159.5, 159.5, 252, 331]}, "name": 1352, "source": {"coordinates": [821.5, 65.5, 109, 170]}, "seconds": 56.333333333333336, "object": "the room", "type": "relation", "subject": "the man"}, {"caption": "the man in the room", "predicate": "in", "target": {"coordinates": [826.5, 211.5, 358, 307]}, "name": 1352, "source": {"coordinates": [587.5, 242.5, 308, 280]}, "seconds": 56.333333333333336, "object": "the room", "type": "relation", "subject": "the man"}, {"caption": "the man has a black", "predicate": "has", "target": {"coordinates": [437.5, 113.5, 152, 171]}, "name": 1352, "source": {"coordinates": [587.5, 242.5, 308, 280]}, "seconds": 56.333333333333336, "object": "a black", "type": "relation", "subject": "the man"}, {"caption": "the man has head", "predicate": "has", "target": {"coordinates": [683.5, 59.5, 87, 182]}, "name": 1352, "source": {"coordinates": [587.5, 242.5, 308, 280]}, "seconds": 56.333333333333336, "object": "head", "type": "relation", "subject": "the man"}, {"caption": "the man in the room", "predicate": "in", "target": {"coordinates": [1127.5, 138.5, 146, 266]}, "name": 1352, "source": {"coordinates": [587.5, 242.5, 308, 280]}, "seconds": 56.333333333333336, "object": "the room", "type": "relation", "subject": "the man"}, {"caption": "the man in white", "predicate": "in", "target": {"coordinates": [821.5, 65.5, 109, 170]}, "name": 1352, "source": {"coordinates": [587.5, 242.5, 308, 280]}, "seconds": 56.333333333333336, "object": "white", "type": "relation", "subject": "the man"}, {"caption": "the shirt on the man", "predicate": "on", "target": {"coordinates": [159.5, 159.5, 252, 331]}, "name": 1352, "source": {"coordinates": [587.5, 242.5, 308, 280]}, "seconds": 56.333333333333336, "object": "the man", "type": "relation", "subject": "the shirt"}, {"caption": "the shirt on the man", "predicate": "on", "target": {"coordinates": [826.5, 211.5, 358, 307]}, "name": 1352, "source": {"coordinates": [159.5, 159.5, 252, 331]}, "seconds": 56.333333333333336, "object": "the man", "type": "relation", "subject": "the shirt"}, {"caption": "the shirt has a black", "predicate": "has", "target": {"coordinates": [437.5, 113.5, 152, 171]}, "name": 1352, "source": {"coordinates": [159.5, 159.5, 252, 331]}, "seconds": 56.333333333333336, "object": "a black", "type": "relation", "subject": "the shirt"}, {"caption": "the shirt has head", "predicate": "has", "target": {"coordinates": [683.5, 59.5, 87, 182]}, "name": 1352, "source": {"coordinates": [159.5, 159.5, 252, 331]}, "seconds": 56.333333333333336, "object": "head", "type": "relation", "subject": "the shirt"}, {"caption": "the shirt on the man", "predicate": "on", "target": {"coordinates": [1127.5, 138.5, 146, 266]}, "name": 1352, "source": {"coordinates": [159.5, 159.5, 252, 331]}, "seconds": 56.333333333333336, "object": "the man", "type": "relation", "subject": "the shirt"}, {"caption": "the shirt on the man", "predicate": "on", "target": {"coordinates": [821.5, 65.5, 109, 170]}, "name": 1352, "source": {"coordinates": [159.5, 159.5, 252, 331]}, "seconds": 56.333333333333336, "object": "the man", "type": "relation", "subject": "the shirt"}, {"caption": "the shirt on man", "predicate": "on", "target": {"coordinates": [587.5, 242.5, 308, 280]}, "name": 1352, "source": {"coordinates": [159.5, 159.5, 252, 331]}, "seconds": 56.333333333333336, "object": "man", "type": "relation", "subject": "the shirt"}]