[{"caption": "the picture on wall", "predicate": "on", "target": {"coordinates": [-0.5, 92.5, 217, 598]}, "name": 3057, "source": {"coordinates": [116.5, 26.5, 723, 690]}, "seconds": 127.375, "object": "wall", "type": "relation", "subject": "the picture"}, {"caption": "the picture on wall", "predicate": "on", "target": {"coordinates": [116.5, 26.5, 723, 690]}, "name": 3057, "source": {"coordinates": [-0.5, 92.5, 217, 598]}, "seconds": 127.375, "object": "wall", "type": "relation", "subject": "the picture"}]