[{"caption": "the people in background", "predicate": "in", "target": {"coordinates": [78.5, 475.5, 102, 247]}, "name": 5274, "source": {"coordinates": [498.5, 490.5, 61, 239]}, "seconds": 219.75, "object": "background", "type": "relation", "subject": "the people"}, {"caption": "the people in background", "predicate": "in", "target": {"coordinates": [383.5, 517.5, 48, 204]}, "name": 5274, "source": {"coordinates": [498.5, 490.5, 61, 239]}, "seconds": 219.75, "object": "background", "type": "relation", "subject": "the people"}, {"caption": "the people in background", "predicate": "in", "target": {"coordinates": [426.5, 515.5, 63, 203]}, "name": 5274, "source": {"coordinates": [498.5, 490.5, 61, 239]}, "seconds": 219.75, "object": "background", "type": "relation", "subject": "the people"}, {"caption": "the people in background", "predicate": "in", "target": {"coordinates": [-0.5, 483.5, 56, 231]}, "name": 5274, "source": {"coordinates": [498.5, 490.5, 61, 239]}, "seconds": 219.75, "object": "background", "type": "relation", "subject": "the people"}, {"caption": "the people in background", "predicate": "in", "target": {"coordinates": [498.5, 490.5, 61, 239]}, "name": 5274, "source": {"coordinates": [78.5, 475.5, 102, 247]}, "seconds": 219.75, "object": "background", "type": "relation", "subject": "the people"}, {"caption": "the people in background", "predicate": "in", "target": {"coordinates": [383.5, 517.5, 48, 204]}, "name": 5274, "source": {"coordinates": [78.5, 475.5, 102, 247]}, "seconds": 219.75, "object": "background", "type": "relation", "subject": "the people"}, {"caption": "the people in background", "predicate": "in", "target": {"coordinates": [426.5, 515.5, 63, 203]}, "name": 5274, "source": {"coordinates": [78.5, 475.5, 102, 247]}, "seconds": 219.75, "object": "background", "type": "relation", "subject": "the people"}, {"caption": "the people in background", "predicate": "in", "target": {"coordinates": [-0.5, 483.5, 56, 231]}, "name": 5274, "source": {"coordinates": [78.5, 475.5, 102, 247]}, "seconds": 219.75, "object": "background", "type": "relation", "subject": "the people"}, {"caption": "the people in background", "predicate": "in", "target": {"coordinates": [498.5, 490.5, 61, 239]}, "name": 5274, "source": {"coordinates": [383.5, 517.5, 48, 204]}, "seconds": 219.75, "object": "background", "type": "relation", "subject": "the people"}, {"caption": "the people in background", "predicate": "in", "target": {"coordinates": [78.5, 475.5, 102, 247]}, "name": 5274, "source": {"coordinates": [383.5, 517.5, 48, 204]}, "seconds": 219.75, "object": "background", "type": "relation", "subject": "the people"}, {"caption": "the people in background", "predicate": "in", "target": {"coordinates": [426.5, 515.5, 63, 203]}, "name": 5274, "source": {"coordinates": [383.5, 517.5, 48, 204]}, "seconds": 219.75, "object": "background", "type": "relation", "subject": "the people"}, {"caption": "the people in background", "predicate": "in", "target": {"coordinates": [-0.5, 483.5, 56, 231]}, "name": 5274, "source": {"coordinates": [383.5, 517.5, 48, 204]}, "seconds": 219.75, "object": "background", "type": "relation", "subject": "the people"}, {"caption": "the people in background", "predicate": "in", "target": {"coordinates": [498.5, 490.5, 61, 239]}, "name": 5274, "source": {"coordinates": [426.5, 515.5, 63, 203]}, "seconds": 219.75, "object": "background", "type": "relation", "subject": "the people"}, {"caption": "the people in background", "predicate": "in", "target": {"coordinates": [78.5, 475.5, 102, 247]}, "name": 5274, "source": {"coordinates": [426.5, 515.5, 63, 203]}, "seconds": 219.75, "object": "background", "type": "relation", "subject": "the people"}, {"caption": "the people in background", "predicate": "in", "target": {"coordinates": [383.5, 517.5, 48, 204]}, "name": 5274, "source": {"coordinates": [426.5, 515.5, 63, 203]}, "seconds": 219.75, "object": "background", "type": "relation", "subject": "the people"}, {"caption": "the people in background", "predicate": "in", "target": {"coordinates": [-0.5, 483.5, 56, 231]}, "name": 5274, "source": {"coordinates": [426.5, 515.5, 63, 203]}, "seconds": 219.75, "object": "background", "type": "relation", "subject": "the people"}, {"caption": "the people in background", "predicate": "in", "target": {"coordinates": [498.5, 490.5, 61, 239]}, "name": 5274, "source": {"coordinates": [-0.5, 483.5, 56, 231]}, "seconds": 219.75, "object": "background", "type": "relation", "subject": "the people"}, {"caption": "the people in background", "predicate": "in", "target": {"coordinates": [78.5, 475.5, 102, 247]}, "name": 5274, "source": {"coordinates": [-0.5, 483.5, 56, 231]}, "seconds": 219.75, "object": "background", "type": "relation", "subject": "the people"}, {"caption": "the people in background", "predicate": "in", "target": {"coordinates": [383.5, 517.5, 48, 204]}, "name": 5274, "source": {"coordinates": [-0.5, 483.5, 56, 231]}, "seconds": 219.75, "object": "background", "type": "relation", "subject": "the people"}, {"caption": "the people in background", "predicate": "in", "target": {"coordinates": [426.5, 515.5, 63, 203]}, "name": 5274, "source": {"coordinates": [-0.5, 483.5, 56, 231]}, "seconds": 219.75, "object": "background", "type": "relation", "subject": "the people"}]