[{"caption": "the bench in front of white wall", "predicate": "in", "target": {"coordinates": [443.5, 116.5, 181, 649]}, "name": 1088, "source": {"coordinates": [232.5, 155.5, 299, 543]}, "seconds": 45.333333333333336, "object": "front of white wall", "type": "relation", "subject": "the bench"}, {"caption": "the bench in front of a bench", "predicate": "in", "target": {"coordinates": [717.5, 133.5, 187, 587]}, "name": 1088, "source": {"coordinates": [232.5, 155.5, 299, 543]}, "seconds": 45.333333333333336, "object": "front of a bench", "type": "relation", "subject": "the bench"}, {"caption": "the bench in background", "predicate": "in", "target": {"coordinates": [593.5, 60.5, 177, 675]}, "name": 1088, "source": {"coordinates": [232.5, 155.5, 299, 543]}, "seconds": 45.333333333333336, "object": "background", "type": "relation", "subject": "the bench"}, {"caption": "the man on top of table", "predicate": "on", "target": {"coordinates": [877.5, 75.5, 181, 690]}, "name": 1088, "source": {"coordinates": [232.5, 155.5, 299, 543]}, "seconds": 45.333333333333336, "object": "top of table", "type": "relation", "subject": "the man"}, {"caption": "the man on top of table", "predicate": "on", "target": {"coordinates": [232.5, 155.5, 299, 543]}, "name": 1088, "source": {"coordinates": [443.5, 116.5, 181, 649]}, "seconds": 45.333333333333336, "object": "top of table", "type": "relation", "subject": "the man"}, {"caption": "the man on brown bench", "predicate": "on", "target": {"coordinates": [717.5, 133.5, 187, 587]}, "name": 1088, "source": {"coordinates": [443.5, 116.5, 181, 649]}, "seconds": 45.333333333333336, "object": "brown bench", "type": "relation", "subject": "the man"}, {"caption": "the man in front of white", "predicate": "in", "target": {"coordinates": [593.5, 60.5, 177, 675]}, "name": 1088, "source": {"coordinates": [443.5, 116.5, 181, 649]}, "seconds": 45.333333333333336, "object": "front of white", "type": "relation", "subject": "the man"}, {"caption": "the people on ground", "predicate": "on", "target": {"coordinates": [877.5, 75.5, 181, 690]}, "name": 1088, "source": {"coordinates": [443.5, 116.5, 181, 649]}, "seconds": 45.333333333333336, "object": "ground", "type": "relation", "subject": "the people"}, {"caption": "the people on ground", "predicate": "on", "target": {"coordinates": [232.5, 155.5, 299, 543]}, "name": 1088, "source": {"coordinates": [717.5, 133.5, 187, 587]}, "seconds": 45.333333333333336, "object": "ground", "type": "relation", "subject": "the people"}, {"caption": "the woman wearing black shirt", "predicate": "wearing", "target": {"coordinates": [443.5, 116.5, 181, 649]}, "name": 1088, "source": {"coordinates": [717.5, 133.5, 187, 587]}, "seconds": 45.333333333333336, "object": "black shirt", "type": "relation", "subject": "the woman"}, {"caption": "the people in front of the building", "predicate": "in", "target": {"coordinates": [593.5, 60.5, 177, 675]}, "name": 1088, "source": {"coordinates": [717.5, 133.5, 187, 587]}, "seconds": 45.333333333333336, "object": "front of the building", "type": "relation", "subject": "the people"}, {"caption": "the person on ground", "predicate": "on", "target": {"coordinates": [877.5, 75.5, 181, 690]}, "name": 1088, "source": {"coordinates": [717.5, 133.5, 187, 587]}, "seconds": 45.333333333333336, "object": "ground", "type": "relation", "subject": "the person"}, {"caption": "the person on ground", "predicate": "on", "target": {"coordinates": [232.5, 155.5, 299, 543]}, "name": 1088, "source": {"coordinates": [593.5, 60.5, 177, 675]}, "seconds": 45.333333333333336, "object": "ground", "type": "relation", "subject": "the person"}, {"caption": "the woman wearing black shirt", "predicate": "wearing", "target": {"coordinates": [443.5, 116.5, 181, 649]}, "name": 1088, "source": {"coordinates": [593.5, 60.5, 177, 675]}, "seconds": 45.333333333333336, "object": "black shirt", "type": "relation", "subject": "the woman"}, {"caption": "the person in front of white wall", "predicate": "in", "target": {"coordinates": [717.5, 133.5, 187, 587]}, "name": 1088, "source": {"coordinates": [593.5, 60.5, 177, 675]}, "seconds": 45.333333333333336, "object": "front of white wall", "type": "relation", "subject": "the person"}, {"caption": "the people on ground", "predicate": "on", "target": {"coordinates": [877.5, 75.5, 181, 690]}, "name": 1088, "source": {"coordinates": [593.5, 60.5, 177, 675]}, "seconds": 45.333333333333336, "object": "ground", "type": "relation", "subject": "the people"}, {"caption": "the people on ground", "predicate": "on", "target": {"coordinates": [232.5, 155.5, 299, 543]}, "name": 1088, "source": {"coordinates": [877.5, 75.5, 181, 690]}, "seconds": 45.333333333333336, "object": "ground", "type": "relation", "subject": "the people"}, {"caption": "the woman wearing blue shirt", "predicate": "wearing", "target": {"coordinates": [443.5, 116.5, 181, 649]}, "name": 1088, "source": {"coordinates": [877.5, 75.5, 181, 690]}, "seconds": 45.333333333333336, "object": "blue shirt", "type": "relation", "subject": "the woman"}, {"caption": "the people in front of white", "predicate": "in", "target": {"coordinates": [717.5, 133.5, 187, 587]}, "name": 1088, "source": {"coordinates": [877.5, 75.5, 181, 690]}, "seconds": 45.333333333333336, "object": "front of white", "type": "relation", "subject": "the people"}, {"caption": "the people on top of brown bench", "predicate": "on", "target": {"coordinates": [593.5, 60.5, 177, 675]}, "name": 1088, "source": {"coordinates": [877.5, 75.5, 181, 690]}, "seconds": 45.333333333333336, "object": "top of brown bench", "type": "relation", "subject": "the people"}]