[{"caption": "the woman in a white chair", "predicate": "in", "target": {"coordinates": [53, 55, 575, 673]}, "name": 1917, "source": {"coordinates": [577, 133, 453, 576]}, "seconds": 79.875, "object": "a white chair", "type": "relation", "subject": "the woman"}, {"caption": "the woman in a white chair", "predicate": "in", "target": {"coordinates": [577, 133, 453, 576]}, "name": 1917, "source": {"coordinates": [53, 55, 575, 673]}, "seconds": 79.875, "object": "a white chair", "type": "relation", "subject": "the woman"}]