[{"caption": "the woman in front of white", "predicate": "in", "target": {"coordinates": [105, 528, 154, 180]}, "name": 2073, "source": {"coordinates": [444, 81, 602, 631]}, "seconds": 86.375, "object": "front of white", "type": "relation", "subject": "the woman"}, {"caption": "the woman in front of white", "predicate": "in", "target": {"coordinates": [996, 436, 276, 283]}, "name": 2073, "source": {"coordinates": [444, 81, 602, 631]}, "seconds": 86.375, "object": "front of white", "type": "relation", "subject": "the woman"}, {"caption": "the people in front of white", "predicate": "in", "target": {"coordinates": [259, 420, 249, 279]}, "name": 2073, "source": {"coordinates": [444, 81, 602, 631]}, "seconds": 86.375, "object": "front of white", "type": "relation", "subject": "the people"}, {"caption": "the people in front of white", "predicate": "in", "target": {"coordinates": [444, 81, 602, 631]}, "name": 2073, "source": {"coordinates": [105, 528, 154, 180]}, "seconds": 86.375, "object": "front of white", "type": "relation", "subject": "the people"}, {"caption": "the people on the a the in background", "predicate": "on", "target": {"coordinates": [996, 436, 276, 283]}, "name": 2073, "source": {"coordinates": [105, 528, 154, 180]}, "seconds": 86.375, "object": "the a the in background", "type": "relation", "subject": "the people"}, {"caption": "the people in front of white", "predicate": "in", "target": {"coordinates": [259, 420, 249, 279]}, "name": 2073, "source": {"coordinates": [105, 528, 154, 180]}, "seconds": 86.375, "object": "front of white", "type": "relation", "subject": "the people"}, {"caption": "the people in front of white", "predicate": "in", "target": {"coordinates": [444, 81, 602, 631]}, "name": 2073, "source": {"coordinates": [996, 436, 276, 283]}, "seconds": 86.375, "object": "front of white", "type": "relation", "subject": "the people"}, {"caption": "the building in background", "predicate": "in", "target": {"coordinates": [105, 528, 154, 180]}, "name": 2073, "source": {"coordinates": [996, 436, 276, 283]}, "seconds": 86.375, "object": "background", "type": "relation", "subject": "the building"}, {"caption": "the people in front of white", "predicate": "in", "target": {"coordinates": [259, 420, 249, 279]}, "name": 2073, "source": {"coordinates": [996, 436, 276, 283]}, "seconds": 86.375, "object": "front of white", "type": "relation", "subject": "the people"}, {"caption": "the people in front of white", "predicate": "in", "target": {"coordinates": [444, 81, 602, 631]}, "name": 2073, "source": {"coordinates": [259, 420, 249, 279]}, "seconds": 86.375, "object": "front of white", "type": "relation", "subject": "the people"}, {"caption": "the building in background", "predicate": "in", "target": {"coordinates": [105, 528, 154, 180]}, "name": 2073, "source": {"coordinates": [259, 420, 249, 279]}, "seconds": 86.375, "object": "background", "type": "relation", "subject": "the building"}, {"caption": "the building in background", "predicate": "in", "target": {"coordinates": [996, 436, 276, 283]}, "name": 2073, "source": {"coordinates": [259, 420, 249, 279]}, "seconds": 86.375, "object": "background", "type": "relation", "subject": "the building"}]