[{"caption": "the man on top of table", "predicate": "on", "target": {"coordinates": [235.5, 73.5, 194, 347]}, "name": 2498, "source": {"coordinates": [687.5, 118.5, 141, 525]}, "seconds": 104.08333333333333, "object": "top of table", "type": "relation", "subject": "the man"}, {"caption": "the woman wearing black shirt", "predicate": "wearing", "target": {"coordinates": [142.5, 333.5, 414, 322]}, "name": 2498, "source": {"coordinates": [687.5, 118.5, 141, 525]}, "seconds": 104.08333333333333, "object": "black shirt", "type": "relation", "subject": "the woman"}, {"caption": "the woman wearing black shirt", "predicate": "wearing", "target": {"coordinates": [687.5, 118.5, 141, 525]}, "name": 2498, "source": {"coordinates": [235.5, 73.5, 194, 347]}, "seconds": 104.08333333333333, "object": "black shirt", "type": "relation", "subject": "the woman"}, {"caption": "the man wearing black shirt", "predicate": "wearing", "target": {"coordinates": [142.5, 333.5, 414, 322]}, "name": 2498, "source": {"coordinates": [235.5, 73.5, 194, 347]}, "seconds": 104.08333333333333, "object": "black shirt", "type": "relation", "subject": "the man"}, {"caption": "the man wearing black shirt", "predicate": "wearing", "target": {"coordinates": [687.5, 118.5, 141, 525]}, "name": 2498, "source": {"coordinates": [142.5, 333.5, 414, 322]}, "seconds": 104.08333333333333, "object": "black shirt", "type": "relation", "subject": "the man"}, {"caption": "the man wearing black shirt", "predicate": "wearing", "target": {"coordinates": [235.5, 73.5, 194, 347]}, "name": 2498, "source": {"coordinates": [142.5, 333.5, 414, 322]}, "seconds": 104.08333333333333, "object": "black shirt", "type": "relation", "subject": "the man"}]