[{"caption": "the man in room", "predicate": "in", "target": {"coordinates": [32.5, 168.5, 476, 537]}, "name": 4046, "source": {"coordinates": [709.5, 72.5, 376, 638]}, "seconds": 168.58333333333334, "object": "room", "type": "relation", "subject": "the man"}, {"caption": "the man in room", "predicate": "in", "target": {"coordinates": [709.5, 72.5, 376, 638]}, "name": 4046, "source": {"coordinates": [32.5, 168.5, 476, 537]}, "seconds": 168.58333333333334, "object": "room", "type": "relation", "subject": "the man"}]