[{"caption": "the man on top of table", "predicate": "on", "target": {"coordinates": [15.5, 52.5, 649, 673]}, "name": 1734, "source": {"coordinates": [540.5, 55.5, 532, 652]}, "seconds": 72.25, "object": "top of table", "type": "relation", "subject": "the man"}, {"caption": "the man on top of table", "predicate": "on", "target": {"coordinates": [540.5, 55.5, 532, 652]}, "name": 1734, "source": {"coordinates": [15.5, 52.5, 649, 673]}, "seconds": 72.25, "object": "top of table", "type": "relation", "subject": "the man"}]