[{"caption": "the people in front of a woman", "predicate": "in", "target": {"coordinates": [811.5, 46.5, 372, 673]}, "name": 3253, "source": {"coordinates": [229.5, 117.5, 551, 606]}, "seconds": 135.54166666666666, "object": "front of a woman", "type": "relation", "subject": "the people"}, {"caption": "the people in front of a woman", "predicate": "in", "target": {"coordinates": [229.5, 117.5, 551, 606]}, "name": 3253, "source": {"coordinates": [811.5, 46.5, 372, 673]}, "seconds": 135.54166666666666, "object": "front of a woman", "type": "relation", "subject": "the people"}]