[{"caption": "the shadow on ground", "predicate": "on", "target": {"coordinates": [679.5, 371.5, 334, 354]}, "name": 506, "source": {"coordinates": [204.5, 304.5, 216, 383]}, "seconds": 21.083333333333332, "object": "ground", "type": "relation", "subject": "the shadow"}, {"caption": "the light on wall", "predicate": "on", "target": {"coordinates": [413.5, 329.5, 228, 381]}, "name": 506, "source": {"coordinates": [204.5, 304.5, 216, 383]}, "seconds": 21.083333333333332, "object": "wall", "type": "relation", "subject": "the light"}, {"caption": "the white shirt has white shirt", "predicate": "has", "target": {"coordinates": [327.5, 113.5, 93, 246]}, "name": 506, "source": {"coordinates": [204.5, 304.5, 216, 383]}, "seconds": 21.083333333333332, "object": "white shirt", "type": "relation", "subject": "the white shirt"}, {"caption": "the building has a a white", "predicate": "has", "target": {"coordinates": [418.5, 119.5, 73, 145]}, "name": 506, "source": {"coordinates": [204.5, 304.5, 216, 383]}, "seconds": 21.083333333333332, "object": "a a white", "type": "relation", "subject": "the building"}, {"caption": "the building has a a white", "predicate": "has", "target": {"coordinates": [204.5, 304.5, 216, 383]}, "name": 506, "source": {"coordinates": [679.5, 371.5, 334, 354]}, "seconds": 21.083333333333332, "object": "a a white", "type": "relation", "subject": "the building"}, {"caption": "the wall has a window", "predicate": "has", "target": {"coordinates": [413.5, 329.5, 228, 381]}, "name": 506, "source": {"coordinates": [679.5, 371.5, 334, 354]}, "seconds": 21.083333333333332, "object": "a window", "type": "relation", "subject": "the wall"}, {"caption": "the building has a white shirt", "predicate": "has", "target": {"coordinates": [327.5, 113.5, 93, 246]}, "name": 506, "source": {"coordinates": [679.5, 371.5, 334, 354]}, "seconds": 21.083333333333332, "object": "a white shirt", "type": "relation", "subject": "the building"}, {"caption": "the bench has a white", "predicate": "has", "target": {"coordinates": [418.5, 119.5, 73, 145]}, "name": 506, "source": {"coordinates": [679.5, 371.5, 334, 354]}, "seconds": 21.083333333333332, "object": "a white", "type": "relation", "subject": "the bench"}, {"caption": "the bench has a white", "predicate": "has", "target": {"coordinates": [204.5, 304.5, 216, 383]}, "name": 506, "source": {"coordinates": [413.5, 329.5, 228, 381]}, "seconds": 21.083333333333332, "object": "a white", "type": "relation", "subject": "the bench"}, {"caption": "the shadow on ground", "predicate": "on", "target": {"coordinates": [679.5, 371.5, 334, 354]}, "name": 506, "source": {"coordinates": [413.5, 329.5, 228, 381]}, "seconds": 21.083333333333332, "object": "ground", "type": "relation", "subject": "the shadow"}, {"caption": "the man wearing black shirt", "predicate": "wearing", "target": {"coordinates": [327.5, 113.5, 93, 246]}, "name": 506, "source": {"coordinates": [413.5, 329.5, 228, 381]}, "seconds": 21.083333333333332, "object": "black shirt", "type": "relation", "subject": "the man"}, {"caption": "the light on wall", "predicate": "on", "target": {"coordinates": [418.5, 119.5, 73, 145]}, "name": 506, "source": {"coordinates": [413.5, 329.5, 228, 381]}, "seconds": 21.083333333333332, "object": "wall", "type": "relation", "subject": "the light"}, {"caption": "the light on wall", "predicate": "on", "target": {"coordinates": [204.5, 304.5, 216, 383]}, "name": 506, "source": {"coordinates": [327.5, 113.5, 93, 246]}, "seconds": 21.083333333333332, "object": "wall", "type": "relation", "subject": "the light"}, {"caption": "the window on building", "predicate": "on", "target": {"coordinates": [679.5, 371.5, 334, 354]}, "name": 506, "source": {"coordinates": [327.5, 113.5, 93, 246]}, "seconds": 21.083333333333332, "object": "building", "type": "relation", "subject": "the window"}, {"caption": "the light on ground", "predicate": "on", "target": {"coordinates": [413.5, 329.5, 228, 381]}, "name": 506, "source": {"coordinates": [327.5, 113.5, 93, 246]}, "seconds": 21.083333333333332, "object": "ground", "type": "relation", "subject": "the light"}, {"caption": "the man on white table", "predicate": "on", "target": {"coordinates": [418.5, 119.5, 73, 145]}, "name": 506, "source": {"coordinates": [327.5, 113.5, 93, 246]}, "seconds": 21.083333333333332, "object": "white table", "type": "relation", "subject": "the man"}, {"caption": "the man on white table", "predicate": "on", "target": {"coordinates": [204.5, 304.5, 216, 383]}, "name": 506, "source": {"coordinates": [418.5, 119.5, 73, 145]}, "seconds": 21.083333333333332, "object": "white table", "type": "relation", "subject": "the man"}, {"caption": "the man on the wall", "predicate": "on", "target": {"coordinates": [679.5, 371.5, 334, 354]}, "name": 506, "source": {"coordinates": [418.5, 119.5, 73, 145]}, "seconds": 21.083333333333332, "object": "the wall", "type": "relation", "subject": "the man"}, {"caption": "the man on white surfboard", "predicate": "on", "target": {"coordinates": [413.5, 329.5, 228, 381]}, "name": 506, "source": {"coordinates": [418.5, 119.5, 73, 145]}, "seconds": 21.083333333333332, "object": "white surfboard", "type": "relation", "subject": "the man"}, {"caption": "the man on wall", "predicate": "on", "target": {"coordinates": [327.5, 113.5, 93, 246]}, "name": 506, "source": {"coordinates": [418.5, 119.5, 73, 145]}, "seconds": 21.083333333333332, "object": "wall", "type": "relation", "subject": "the man"}]