[{"caption": "the woman has a head", "predicate": "has", "target": {"coordinates": [862.5, -0.5, 420, 567]}, "name": 2160, "source": {"coordinates": [335.5, 56.5, 657, 664]}, "seconds": 90.0, "object": "a head", "type": "relation", "subject": "the woman"}, {"caption": "the people on top of brown table", "predicate": "on", "target": {"coordinates": [526.5, 6.5, 364, 330]}, "name": 2160, "source": {"coordinates": [335.5, 56.5, 657, 664]}, "seconds": 90.0, "object": "top of brown table", "type": "relation", "subject": "the people"}, {"caption": "the people on top of brown table", "predicate": "on", "target": {"coordinates": [335.5, 56.5, 657, 664]}, "name": 2160, "source": {"coordinates": [862.5, -0.5, 420, 567]}, "seconds": 90.0, "object": "top of brown table", "type": "relation", "subject": "the people"}, {"caption": "the woman on brown bench", "predicate": "on", "target": {"coordinates": [526.5, 6.5, 364, 330]}, "name": 2160, "source": {"coordinates": [862.5, -0.5, 420, 567]}, "seconds": 90.0, "object": "brown bench", "type": "relation", "subject": "the woman"}, {"caption": "the woman on brown bench", "predicate": "on", "target": {"coordinates": [335.5, 56.5, 657, 664]}, "name": 2160, "source": {"coordinates": [526.5, 6.5, 364, 330]}, "seconds": 90.0, "object": "brown bench", "type": "relation", "subject": "the woman"}, {"caption": "the woman in front of white", "predicate": "in", "target": {"coordinates": [862.5, -0.5, 420, 567]}, "name": 2160, "source": {"coordinates": [526.5, 6.5, 364, 330]}, "seconds": 90.0, "object": "front of white", "type": "relation", "subject": "the woman"}]